effector/__init__.py
effector/axis_partitioning.py
effector/datasets.py
effector/global_effect.py
effector/global_effect_ale.py
effector/global_effect_pdp.py
effector/global_effect_shap.py
effector/helpers.py
effector/interaction.py
effector/models.py
effector/regional_effect.py
effector/regional_effect_ale.py
effector/regional_effect_pdp.py
effector/regional_effect_shap.py
effector/space_partitioning.py
effector/tree.py
effector/utils.py
effector/utils_integrate.py
effector/visualization.py
effector-0.1.12.dist-info/licenses/LICENSE
effector-0.1.12.dist-info/WHEEL
effector-0.1.12.dist-info/METADATA
effector-0.1.12.dist-info/RECORD
