Metadata-Version: 2.4
Name: effector
Version: 0.1.12
Summary: An eXplainable AI package for tabular data.
Keywords: explainability,interpretability,machine learning,deep learning,regional XAI,feature effect
Author-email: Vasilis Gkolemis <ntipakos@gmail.com>
Maintainer-email: Christos Diou <cdiou@hua.gr>, Julia Herbinger <julia.herbinger@gmail.com>, Giuseppe Casalicchio <giuseppe.casalicchio@gmail.com>, Hubert Baniecki <h.baniecki@uw.edu.pl>, Dimitris Kyriakopoulos <dimitrisskyriakopoulos@gmail.com>, Dimitrios Rontogiannis <dimronto@gmail.com>
Requires-Python: >=3.10
License-File: LICENSE
Requires-Dist: matplotlib
Requires-Dist: numpy
Requires-Dist: scipy
Requires-Dist: tqdm
Requires-Dist: shap
Requires-Dist: shapiq
Requires-Dist: ucimlrepo
Requires-Dist: overrides
Requires-Dist: ipython ; extra == "tutorials"
Requires-Dist: pandas ; extra == "tutorials"
Requires-Dist: tensorflow-cpu ; extra == "tutorials"
Requires-Dist: keras ; extra == "tutorials"
Requires-Dist: ucimlrepo ; extra == "tutorials"
Requires-Dist: jupyter ; extra == "tutorials"
Requires-Dist: openml ; extra == "tutorials"
Requires-Dist: tabpfn ; extra == "tutorials"
Project-URL: documentation, https://xai-effector.github.io
Project-URL: source, https://github.com/givasile/effector
Project-URL: tracker, https://github.com/givasile/effector/issues
Provides-Extra: tutorials
